holjjagml-0.1.1.dist-info/METADATA
holjjagml-0.1.1.dist-info/WHEEL
holjjagml-0.1.1.dist-info/entry_points.txt
holjjagml/__init__.py
holjjagml/cli.py
holjjagml-0.1.1.dist-info/RECORD
