Metadata-Version: 2.1
Name: holjjagml
Version: 0.1.1
Summary: I want to learn. If you let me know, I will learn and sort it out.
Author-Email: dMario24 <data.mario24@gmail.com>
License: GNU
Project-URL: Homepage, https://github.com/dMario24/holjjagml
Project-URL: Issues, https://github.com/dMario24/holjjagml/issues
Requires-Python: >=3.11
Requires-Dist: tqdm>=4.66.5
Requires-Dist: pyfiglet>=1.0.2
